Workbook

Sheet How to answer
A1: Phoenix Skyblock · decisions
A2: Each row is a choice the game uses right now. Answer in the yellow column with one pick:
A3: Suggested = keep it as written in "Suggested".
A4: No = don't do it that way.
A5: Other = write what you want in "Note".
A6: Empty rows keep the suggested answer. Filter Priority = "before launch" to do the important ones first.
A7: Faster on a phone: the clickable page "Phoenix Skyblock Decisions" has the same questions with one tap per answer.
A9: Example of a filled row:
A10: Question | B10: Suggested | C10: Your answer | D10: Note
A11: Keep the AFK pool limit at 8 hours per day? | B11: Yes, 8 hours | C11: Other | D11: 6 hours

Sheet Summary
A1: Area | B1: Questions | C1: Answered | D1: Answered % | E1: Before launch | F1: Before launch answered
A2: Look & feel | B2: =COUNTIF(Questions!$B$2:$B$1014,A2) -> 112 | C2: =COUNTIFS(Questions!$B$2:$B$1014,A2,Questions!$F$2:$F$1014,"<>") -> 0 | D2: =IF(B2=0,0,C2/B2) -> 0 | E2: =COUNTIFS(Questions!$B$2:$B$1014,A2,Questions!$H$2:$H$1014,"before launch") -> 24 | F2: =COUNTIFS(Questions!$B$2:$B$1014,A2,Questions!$H$2:$H$1014,"before launch",Questions!$F$2:$F$1014,"<>") -> 0
A3: Profiles | B3: =COUNTIF(Questions!$B$2:$B$1014,A3) -> 25 | C3: =COUNTIFS(Questions!$B$2:$B$1014,A3,Questions!$F$2:$F$1014,"<>") -> 0 | D3: =IF(B3=0,0,C3/B3) -> 0 | E3: =COUNTIFS(Questions!$B$2:$B$1014,A3,Questions!$H$2:$H$1014,"before launch") -> 14 | F3: =COUNTIFS(Questions!$B$2:$B$1014,A3,Questions!$H$2:$H$1014,"before launch",Questions!$F$2:$F$1014,"<>") -> 0
A4: Islands | B4: =COUNTIF(Questions!$B$2:$B$1014,A4) -> 156 | C4: =COUNTIFS(Questions!$B$2:$B$1014,A4,Questions!$F$2:$F$1014,"<>") -> 0 | D4: =IF(B4=0,0,C4/B4) -> 0 | E4: =COUNTIFS(Questions!$B$2:$B$1014,A4,Questions!$H$2:$H$1014,"before launch") -> 57 | F4: =COUNTIFS(Questions!$B$2:$B$1014,A4,Questions!$H$2:$H$1014,"before launch",Questions!$F$2:$F$1014,"<>") -> 0
A5: Social & chat | B5: =COUNTIF(Questions!$B$2:$B$1014,A5) -> 30 | C5: =COUNTIFS(Questions!$B$2:$B$1014,A5,Questions!$F$2:$F$1014,"<>") -> 0 | D5: =IF(B5=0,0,C5/B5) -> 0 | E5: =COUNTIFS(Questions!$B$2:$B$1014,A5,Questions!$H$2:$H$1014,"before launch") -> 12 | F5: =COUNTIFS(Questions!$B$2:$B$1014,A5,Questions!$H$2:$H$1014,"before launch",Questions!$F$2:$F$1014,"<>") -> 0
A6: Teleports & essentials | B6: =COUNTIF(Questions!$B$2:$B$1014,A6) -> 23 | C6: =COUNTIFS(Questions!$B$2:$B$1014,A6,Questions!$F$2:$F$1014,"<>") -> 0 | D6: =IF(B6=0,0,C6/B6) -> 0 | E6: =COUNTIFS(Questions!$B$2:$B$1014,A6,Questions!$H$2:$H$1014,"before launch") -> 9 | F6: =COUNTIFS(Questions!$B$2:$B$1014,A6,Questions!$H$2:$H$1014,"before launch",Questions!$F$2:$F$1014,"<>") -> 0
A7: Ranks, perks & cosmetics | B7: =COUNTIF(Questions!$B$2:$B$1014,A7) -> 49 | C7: =COUNTIFS(Questions!$B$2:$B$1014,A7,Questions!$F$2:$F$1014,"<>") -> 0 | D7: =IF(B7=0,0,C7/B7) -> 0 | E7: =COUNTIFS(Questions!$B$2:$B$1014,A7,Questions!$H$2:$H$1014,"before launch") -> 14 | F7: =COUNTIFS(Questions!$B$2:$B$1014,A7,Questions!$H$2:$H$1014,"before launch",Questions!$F$2:$F$1014,"<>") -> 0
A8: Worlds & builds | B8: =COUNTIF(Questions!$B$2:$B$1014,A8) -> 12 | C8: =COUNTIFS(Questions!$B$2:$B$1014,A8,Questions!$F$2:$F$1014,"<>") -> 0 | D8: =IF(B8=0,0,C8/B8) -> 0 | E8: =COUNTIFS(Questions!$B$2:$B$1014,A8,Questions!$H$2:$H$1014,"before launch") -> 5 | F8: =COUNTIFS(Questions!$B$2:$B$1014,A8,Questions!$H$2:$H$1014,"before launch",Questions!$F$2:$F$1014,"<>") -> 0
A9: Staff & punishments | B9: =COUNTIF(Questions!$B$2:$B$1014,A9) -> 125 | C9: =COUNTIFS(Questions!$B$2:$B$1014,A9,Questions!$F$2:$F$1014,"<>") -> 0 | D9: =IF(B9=0,0,C9/B9) -> 0 | E9: =COUNTIFS(Questions!$B$2:$B$1014,A9,Questions!$H$2:$H$1014,"before launch") -> 37 | F9: =COUNTIFS(Questions!$B$2:$B$1014,A9,Questions!$H$2:$H$1014,"before launch",Questions!$F$2:$F$1014,"<>") -> 0
A10: Economy | B10: =COUNTIF(Questions!$B$2:$B$1014,A10) -> 196 | C10: =COUNTIFS(Questions!$B$2:$B$1014,A10,Questions!$F$2:$F$1014,"<>") -> 0 | D10: =IF(B10=0,0,C10/B10) -> 0 | E10: =COUNTIFS(Questions!$B$2:$B$1014,A10,Questions!$H$2:$H$1014,"before launch") -> 97 | F10: =COUNTIFS(Questions!$B$2:$B$1014,A10,Questions!$H$2:$H$1014,"before launch",Questions!$F$2:$F$1014,"<>") -> 0
A11: The Depths | B11: =COUNTIF(Questions!$B$2:$B$1014,A11) -> 85 | C11: =COUNTIFS(Questions!$B$2:$B$1014,A11,Questions!$F$2:$F$1014,"<>") -> 0 | D11: =IF(B11=0,0,C11/B11) -> 0 | E11: =COUNTIFS(Questions!$B$2:$B$1014,A11,Questions!$H$2:$H$1014,"before launch") -> 30 | F11: =COUNTIFS(Questions!$B$2:$B$1014,A11,Questions!$H$2:$H$1014,"before launch",Questions!$F$2:$F$1014,"<>") -> 0
A12: Tools, skills & enchants | B12: =COUNTIF(Questions!$B$2:$B$1014,A12) -> 99 | C12: =COUNTIFS(Questions!$B$2:$B$1014,A12,Questions!$F$2:$F$1014,"<>") -> 0 | D12: =IF(B12=0,0,C12/B12) -> 0 | E12: =COUNTIFS(Questions!$B$2:$B$1014,A12,Questions!$H$2:$H$1014,"before launch") -> 38 | F12: =COUNTIFS(Questions!$B$2:$B$1014,A12,Questions!$H$2:$H$1014,"before launch",Questions!$F$2:$F$1014,"<>") -> 0
A13: Wardrobe & sets | B13: =COUNTIF(Questions!$B$2:$B$1014,A13) -> 50 | C13: =COUNTIFS(Questions!$B$2:$B$1014,A13,Questions!$F$2:$F$1014,"<>") -> 0 | D13: =IF(B13=0,0,C13/B13) -> 0 | E13: =COUNTIFS(Questions!$B$2:$B$1014,A13,Questions!$H$2:$H$1014,"before launch") -> 27 | F13: =COUNTIFS(Questions!$B$2:$B$1014,A13,Questions!$H$2:$H$1014,"before launch",Questions!$F$2:$F$1014,"<>") -> 0
... A15: AFK pool | B15: =COUNTIF(Questions!$B$2:$B$1014,A15) -> 21 | C15: =COUNTIFS(Questions!$B$2:$B$1014,A15,Questions!$F$2:$F$1014,"<>") -> 0 | D15: =IF(B15=0,0,C15/B15) -> 0 | E15: =COUNTIFS(Questions!$B$2:$B$1014,A15,Questions!$H$2:$H$1014,"before launch") -> 14 | F15: =COUNTIFS(Questions!$B$2:$B$1014,A15,Questions!$H$2:$H$1014,"before launch",Questions!$F$2:$F$1014,"<>") -> 0
A16: Total | B16: =SUM(B2:B15) -> 1013 | C16: =SUM(C2:C15) -> 0 | D16: =IF(B16=0,0,C16/B16) -> 0 | E16: =SUM(E2:E15) -> 390 | F16: =SUM(F2:F15) -> 0

Sheet Questions
A1: # | B1: Area | C1: Feature | D1: Question | E1: Suggested | F1: Your answer | G1: Note | H1: Priority | I1: Context
A2: 1 | B2: Look & feel | C2: Colors and lores (V2) | D2: Show sell price lines in red in item tooltips? | E2: Yes, red | H2: before launch
A3: 2 | B3: Look & feel | C3: Colors and lores (V2) | D3: Show action lines in bold yellow, like '» RIGHT-CLICK buy 64'? | E3: Yes, bold yellow | H3: before launch
A4: 3 | B4: Look & feel | C4: Colors and lores (V2) | D4: Put the thin red bar on every line inside a tooltip section? | E4: Yes, every line | H4: before launch
A5: 4 | B5: Look & feel | C5: Look & feel (colors, lores, menus) | D5: Should the big-sale chat message apply to every /sell sale, not only the sell chest? | E5: Yes, all sales | H5: can wait
A6: 5 | B6: Look & feel | C6: Look & feel (colors, lores, menus) | D6: If a player switches profile with the sell chest open, keep their items for that profile? | E6: Yes, never lost | H6: before launch | I6: Items return at the next switch back.
A7: 6 | B7: Look & feel | C7: Look & feel (colors, lores, menus) | D7: Should 'Sell inventory' keep tools, weapons and armor in the hotbar? | E7: Yes, keep them | H7: before launch
A8: 7 | B8: Look & feel | C8: Look & feel (colors, lores, menus) | D8: If returned items don't fit the inventory, put them in the ender chest first, then drop them? | E8: Yes | H8: before launch
A9: 8 | B9: Look & feel | C9: Look & feel (colors, lores, menus) | D9: Should shop quick-buy ask for confirmation only for purchases of $100k or more? | E9: Yes, $100k | H9: before launch
A10: 9 | B10: Look & feel | C10: Look & feel (colors, lores, menus) | D10: If a player can't afford 64 items, refuse the purchase instead of buying what they can afford? | E10: Yes, refuse | H10: before launch
A11: 10 | B11: Look & feel | C11: Look & feel (colors, lores, menus) | D11: Add a quick 'Buy 1' option for Bedrock players too? | E11: No, amount screen only | H11: can wait
A12: 11 | B12: Look & feel | C12: Look & feel (colors, lores, menus) | D12: Should players be able to drag satchel items into the sell chest? | E12: No, sell them from the satchel | H12: can wait
A13: 12 | B13: Look & feel | C13: Look & feel (colors, lores, menus) | D13: Keep the server's main color red on Bedrock, the same as errors? | E13: Yes, red | H13: can wait | I13: Errors still differ by the ✘ mark.
A14: 13 | B14: Look & feel | C14: Look & feel (colors, lores, menus) | D14: Should the shop's sell price be shown before the player's own sell bonus? | E14: Yes, before bonus | H14: can wait
A15: 14 | B15: Look & feel | C15: Look & feel (colors, lores, menus) | D15: Is the island scoreboard fine with no blank line, and Depths boards showing money only? | E15: Yes, as built | H15: can wait
A16: 15 | B16: Look & feel | C16: Look & feel (colors, lores, menus) | D16: Keep the scoreboard footer in ice blue? | E16: Yes, ice blue | H16: can wait
A17: 16 | B17: Look & feel | C17: Look & feel (colors, lores, menus) | D17: Use yellow-gold for filled progress dots rather than orange? | E17: Yes, yellow-gold | H17: can wait
A18: 17 | B18: Look & feel | C18: Look & feel (colors, lores, menus) | D18: Let item descriptions wrap over up to 3 lines instead of 2? | E18: Yes, 3 lines | H18: can wait
A19: 18 | B19: Look & feel | C19: Look & feel (colors, lores, menus) | D19: Move all menu lore into one shared code builder later? | E19: No, the look already matches | H19: can wait
A20: 19 | B20: Look & feel | C20: Look & feel (colors, lores, menus) | D20: Is it OK that crate, quest and leaderboard holograms come later? | E20: Yes | H20: can wait
A21: 20 | B21: Look & feel | C21: Look & feel (colors, lores, menus) | D21: Keep scoreboard text in the message files, like all other player text? | E21: Yes | H21: can wait
A22: 21 | B22: Look & feel | C22: Look & feel (colors, lores, menus) | D22: Should coop players see the visitor scoreboard on the island they are cooped to? | E22: Yes, visitor board | H22: can wait
A23: 22 | B23: Look & feel | C23: Look & feel (colors, lores, menus) | D23: On someone else's island, show only the island name on the scoreboard? | E23: Yes, island name only | H23: can wait
A24: 23 | B24: Look & feel | C24: Look & feel (colors, lores, menus) | D24: Keep Gems on the island scoreboard, with the 'Next' note line only when there is a note? | E24: Yes | H24: can wait
A25: 24 | B25: Look & feel | C25: Look & feel (colors, lores, menus) | D25: Keep the Depths scoreboard choosing its zone layout from the zone name text? | E25: Yes, text match | H25: can wait
... A27: 26 | B27: Look & feel | C27: Look & feel (colors, lores, menus) | D27: Use aqua ◆ for crystals and green ✦ for gems, with new menu icons? | E27: Yes | H27: can wait
A28: 27 | B28: Look & feel | C28: Look & feel (colors, lores, menus) | D28: Build the crystal island shop and missions later, with the island upgrades? | E28: Yes | H28: can wait | I28: Crystals are only a balance for now.
A29: 28 | B29: Look & feel | C29: Look & feel (colors, lores, menus) | D29: Show SKYBORN in the tab list as white on the left and blue 'MC' on the right? | E29: Yes | H29: can wait
A30: 29 | B30: Look & feel | C30: Look & feel (colors, lores, menus) | D30: Keep the 'Next' objective and online count off the scoreboard for now? | E30: Yes, objective returns with quests | H30: can wait
A31: 30 | B31: Look & feel | C31: Look & feel (colors, lores, menus) | D31: Show join and quit as just [+] Name and [-] Name? | E31: Yes | H31: can wait
A32: 31 | B32: Look & feel | C32: Look and feel V2 (colors, lore, menus, scoreboard) | D32: Launch with English only and add Norwegian later? | E32: Yes, English only at launch | H32: before launch | I32: Translating all messages is a big task.
A33: 32 | B33: Look & feel | C33: Look and feel V2 (colors, lore, menus, scoreboard) | D33: Show big numbers short in menus (1.2M) and in full in chat and /bal? | E33: Yes | H33: before launch
A34: 33 | B34: Look & feel | C34: Look and feel V2 (colors, lore, menus, scoreboard) | D34: Use normal chest menus for Bedrock players too, not special pop-up forms? | E34: Yes, chest menus everywhere | H34: before launch
A35: 34 | B35: Look & feel | C35: Look and feel V2 (colors, lore, menus, scoreboard) | D35: Use a compact, shorter item lore for Bedrock phone players? | E35: Yes, compact mode | H35: before launch
A36: 35 | B36: Look & feel | C36: Look and feel V2 (colors, lore, menus, scoreboard) | D36: Add a high-contrast or color-blind mode in /settings later? | E36: Yes, later | H36: can wait
A37: 36 | B37: Look & feel | C37: Look and feel V2 (colors, lore, menus, scoreboard) | D37: Let players hide single scoreboard lines, such as gems? | E37: Yes, a toggle per line | H37: can wait
A38: 37 | B38: Look & feel | C38: Look and feel V2 (colors, lore, menus, scoreboard) | D38: Add seasonal color palettes, such as a December theme? | E38: Yes, small color swaps | H38: can wait
A39: 38 | B39: Look & feel | C39: Look and feel V2 (colors, lore, menus, scoreboard) | D39: Set menu click sounds to 50% volume for new players? | E39: Yes, 50% | H39: can wait
A40: 39 | B40: Look & feel | C40: Look and feel V2 (colors, lore, menus, scoreboard) | D40: Open the Help page automatically the first time a player joins? | E40: Yes, only once | H40: can wait
A41: 40 | B41: Look & feel | C41: Look and feel V2 (colors, lore, menus, scoreboard) | D41: Show every money change on the action bar, grouped every 1.5 seconds? | E41: Yes | H41: can wait
A42: 41 | B42: Look & feel | C42: Main menu (/menu), menu item and /help | D42: Hide unfinished features (Quests, Crates, Pets...) from the main menu at launch? | E42: Yes, 'Coming soon' in testing, hidden at launch | H42: before launch
A43: 43 | B43: Look & feel | C43: Main menu (/menu), menu item and /help | D43: Add a 5-step 'Start here' help topic: starter kit, island, mine, sell, upgrade? | E43: Yes | H43: before launch | I43: The tutorial should take under 3 minutes.
A44: 44 | B44: Look & feel | C44: Main menu (/menu), menu item and /help | D44: Should every feature be usable from menus on Bedrock, with no long commands to type? | E44: Yes | H44: before launch
A45: 45 | B45: Look & feel | C45: Main menu (/menu), menu item and /help | D45: Give everyone a Nether Star menu item in slot 9 on every join? | E45: Yes, fixed in place, can be turned off in /settings | H45: can wait
A46: 46 | B46: Look & feel | C46: Main menu (/menu), menu item and /help | D46: Should the top-center /menu button show name, rank, money, crystals and island level? | E46: Yes | H46: can wait
A47: 47 | B47: Look & feel | C47: Main menu (/menu), menu item and /help | D47: Keep the menu layout always the same, not remembering the last page used? | E47: Yes, always the same | H47: can wait
A48: 48 | B48: Look & feel | C48: Main menu (/menu), menu item and /help | D48: Add one staff-editable 'Featured' button at the top of the menu for events and news? | E48: Yes | H48: can wait
A49: 49 | B49: Look & feel | C49: Main menu (/menu), menu item and /help | D49: Should admins edit normal settings in /admin, with owner-level settings reserved for you? | E49: Yes, as built | H49: can wait
A50: 50 | B50: Look & feel | C50: Personal settings (/settings) | D50: Make chat, social and sound settings follow the account, with scoreboard and menu item per profile? | E50: Yes | H50: before launch | I50: Players won't need to turn off private messages on every profile.
A51: 51 | B51: Look & feel | C51: Personal settings (/settings) | D51: Add a 'Hide other players' option with a quick toggle at spawn? | E51: Yes, default 'all' | H51: before launch | I51: Reduces lag with hundreds of players at spawn.
A52: 52 | B52: Look & feel | C52: Personal settings (/settings) | D52: Keep the new-player settings as now (tips and particles on)? | E52: Yes, same as now | H52: can wait
A53: 53 | B53: Look & feel | C53: Personal settings (/settings) | D53: Add a one-switch 'Do not disturb' setting for sounds, mentions and requests? | E53: Yes | H53: can wait
A54: 55 | B54: Look & feel | C54: Personal settings (/settings) | D54: Let players turn off the skill XP action bar and other players' trail particles? | E54: Yes, already built | H54: can wait
A55: 56 | B55: Look & feel | C55: Personal settings (/settings) | D55: Add a 'Reset all settings' button with a confirm? | E55: Yes | H55: can wait
A56: 57 | B56: Look & feel | C56: Personal settings (/settings) | D56: Let staff see a player's settings, read-only, in /inspect? | E56: Yes | H56: can wait
A57: 58 | B57: Look & feel | C57: Resource pack (plan) | D57: Make the Java resource pack optional, re-offered once a day to those who decline? | E57: Yes, optional | H57: can wait | I57: Bedrock already forces it.
A58: 59 | B58: Look & feel | C58: Resource pack (plan) | D58: Send the resource pack from the plugin rather than from the server settings? | E58: Yes, from the plugin | H58: can wait
A59: 60 | B59: Look & feel | C59: Resource pack (plan) | D59: Create custom item looks with model tags on normal items, safe if the pack is missing? | E59: Yes | H59: can wait
A60: 61 | B60: Look & feel | C60: Resource pack (plan) | D60: Keep the resource pack files in the main project folder? | E60: Yes, one folder, one release | H60: can wait
A61: 62 | B61: Look & feel | C61: Resource pack (plan) | D61: Host the pack at pack.skybornmc.net on the VPS, with Cloudflare later? | E61: Yes; needs a DNS record from you | H61: can wait
A62: 63 | B62: Look & feel | C62: Resource pack (plan) | D62: Let players switch the pack on or off in /settings? | E62: Yes | H62: can wait
A63: 64 | B63: Look & feel | C63: Resource pack (plan) | D63: Use simple original placeholder art until you or an artist make the real art? | E63: Yes, no Mojang textures | H63: can wait
A64: 65 | B64: Look & feel | C64: Resource pack (plan) | D64: Use dark charcoal menu panels with ember corners? | E64: Yes | H64: can wait
A65: 66 | B65: Look & feel | C65: Resource pack (plan) | D65: Convert the pack for Bedrock with our own small converter? | E65: Yes | H65: can wait | I65: Icons, glyphs and sounds only.
A66: 67 | B66: Look & feel | C66: Resource pack (plan) | D66: Keep Depths drops looking vanilla, except voidstone, raider scrap and wither ash? | E66: Yes | H66: can wait
A67: 68 | B67: Look & feel | C67: Resource pack (plan) | D67: Give pack users custom back/next arrows, and others the player heads? | E67: Yes | H67: can wait
A68: 69 | B68: Look & feel | C68: Resource pack (plan) | D68: Change tool looks by tier only, with a spark overlay for prestige? | E68: Yes | H68: can wait
A69: 70 | B69: Look & feel | C69: Resource pack (plan) | D69: Keep status marks (✔ ✘ ★ ⌛) as plain text symbols? | E69: Yes | H69: can wait
A70: 71 | B70: Look & feel | C70: Resource pack (plan) | D70: Add a custom ember-pattern world border texture? | E70: Yes | H70: can wait
A71: 72 | B71: Look & feel | C71: Resource pack (plan) | D71: Add custom tooltip backgrounds per rarity? | E71: No, not while the pack is optional | H71: can wait
A72: 73 | B72: Look & feel | C72: Resource pack (plan) | D72: Paint the player-inventory half of menus too? | E72: No, top half only | H72: can wait
A73: 74 | B73: Look & feel | C73: Resource pack (plan) | D73: Show rank badges as pictures in chat and tab for pack users? | E73: Yes | H73: can wait | I73: Others still see the text prefix.
A74: 75 | B74: Look & feel | C74: Resource pack plan | D74: Keep the Bedrock pack small, aiming at 5 MB (limit 8 MB)? | E74: Yes, target 5 MB | H74: before launch | I74: Big downloads on mobile data make players leave.
A75: 76 | B75: Look & feel | C75: Resource pack plan | D75: Use vanilla-like 16x16 pixel art with ember colors for the pack? | E75: Yes | H75: before launch
A76: 77 | B76: Look & feel | C76: Resource pack plan | D76: Allow only original or licensed art, no AI-generated art? | E76: Yes, no AI art | H76: before launch
A77: 78 | B77: Look & feel | C77: Resource pack plan | D77: Should you or one trusted tester check each pack release on a Bedrock phone first? | E77: Yes | H77: before launch
A78: 79 | B78: Look & feel | C78: Resource pack plan | D78: Host the pack on the VPS first and add a CDN once over 200 players? | E78: Yes | H78: can wait
A79: 80 | B79: Look & feel | C79: Resource pack plan | D79: Give a one-time cosmetic tag for accepting the resource pack? | E79: Yes | H79: can wait
A80: 81 | B80: Look & feel | C80: Resource pack plan | D80: Should the pack only add new sounds, not replace vanilla sounds? | E80: Yes, only add new | H80: can wait
A81: 82 | B81: Look & feel | C81: Resource pack plan | D81: Limit pack changes to one update per month? | E81: Yes, monthly | H81: can wait | I81: Each update means a re-download.
A82: 83 | B82: Look & feel | C82: Resource pack plan | D82: Leave store-sold hats and backpacks out of the first pack version? | E82: Yes | H82: can wait
A83: 84 | B83: Look & feel | C83: Resource pack plan | D83: Ship just one small pack, with no lite version? | E83: Yes, one 5 MB pack | H83: can wait
A84: 86 | B84: Look & feel | C84: Scoreboards (sidebar) | D84: On scoreboards, show numbers in full below $100k and short above? | E84: Yes, as built | H84: can wait
A85: 87 | B85: Look & feel | C85: Scoreboards (sidebar) | D85: Show the season countdown on the spawn scoreboard only? | E85: Yes | H85: can wait
A86: 88 | B86: Look & feel | C86: Scoreboards (sidebar) | D86: Should the warzone scoreboard show kills, bounty, event timer and combat tag? | E86: Yes | H86: can wait
A87: 89 | B87: Look & feel | C87: Scoreboards (sidebar) | D87: Show satchel fullness on the Depths scoreboard, turning red at 90%? | E87: Yes, red at 90% | H87: can wait | I87: Players lose drops when the satchel is full.
A88: 90 | B88: Look & feel | C88: Scoreboards (sidebar) | D88: Show an island rank line ('Rank #34') on the island scoreboard once the top list exists? | E88: Yes | H88: can wait
A89: 91 | B89: Look & feel | C89: Scoreboards (sidebar) | D89: Show staff in staff mode a separate board with reports, TPS and frozen players? | E89: Yes | H89: can wait
A90: 92 | B90: Look & feel | C90: Scoreboards (sidebar) | D90: Keep one scoreboard layout per place, with no short/long choice? | E90: Yes | H90: can wait
A91: 93 | B91: Look & feel | C91: Scoreboards (sidebar) | D91: Hide the scoreboard when a menu or book is open? | E91: No | H91: can wait
A92: 94 | B92: Look & feel | C92: Server list MOTD and join flow | D92: Keep the whitelist until closed beta, then open with a launch countdown in the server list? | E92: Yes | H92: before launch
A93: 95 | B93: Look & feel | C93: Server list MOTD and join flow | D93: Use 'PHOENIX SKYBLOCK - Season 1 starts DATE - Java and Bedrock' as the launch server-list text? | E93: Yes | H93: before launch | I93: The date still needs filling in.
A94: 96 | B94: Look & feel | C94: Server list MOTD and join flow | D94: Add a one-command maintenance mode that only staff can join? | E94: Yes | H94: before launch
A95: 97 | B95: Look & feel | C95: Server list MOTD and join flow | D95: Show only 'Java & Bedrock' in the server list, with exact versions on the website? | E95: Yes | H95: can wait
A96: 98 | B96: Look & feel | C96: Server list MOTD and join flow | D96: Show the real max player count in the server list? | E96: Yes, the real number | H96: can wait
A97: 99 | B97: Look & feel | C97: Server list MOTD and join flow | D97: Leave vanished staff out of the server-list player count? | E97: Yes | H97: can wait
A98: 100 | B98: Look & feel | C98: Server list MOTD and join flow | D98: Teleport every player to spawn when they join? | E98: Yes, spawn on join | H98: can wait
A99: 101 | B99: Look & feel | C99: Server list MOTD and join flow | D99: Add a rules reminder line, 'Be kind. /rules', to the first-join welcome? | E99: Yes | H99: can wait
A100: 102 | B100: Look & feel | C100: Server list MOTD and join flow | D100: Show the 'Welcome back' title to returning players only once per day? | E100: Yes | H100: can wait
A101: 103 | B101: Look & feel | C101: Server list MOTD and join flow | D101: Show a 'pre-season ends in X days' line on join during the pre-season week? | E101: Yes | H101: can wait | I101: The pre-season ends with a wipe.
...
